{
    "derniere_mise_a_jour": "07/04/2026 à 23:00",
    "horodatage_fin_recherche": "2026-04-07T23:00:00",
    "total_france_twh": 109.986,
    "nombre_centrales_actives": 18,
    "nombre_reacteurs_total": 57,
    "nombre_reacteurs_en_production": 44,
    "production_par_centrale_twh": {
        "GRAVELINES": 10.048,
        "CATTENOM": 8.797,
        "PALUEL": 8.392,
        "BUGEY": 7.22,
        "TRICASTIN": 7.093,
        "CHINON": 7.08,
        "DAMPIERRE": 6.489,
        "CIVAUX": 6.12,
        "CRUAS": 6.092,
        "BLAYAIS": 5.948,
        "NOGENT": 5.725,
        "PENLY": 5.009,
        "BELLEVILLE": 4.987,
        "GOLFECH": 4.642,
        "ST ALBAN": 4.393,
        "FLAMANVILLE": 4.179,
        "CHOOZ": 3.969,
        "ST LAURENT": 3.802
    },
    "cache_brut_mwh": {
        "BELLEVILLE 1": 2612210.0,
        "BELLEVILLE 2": 2375004.0,
        "BLAYAIS 1": 1822077.0,
        "BLAYAIS 2": 1935867.0,
        "BLAYAIS 3": 277894.0,
        "BLAYAIS 4": 1912316.0,
        "BUGEY 2": 2065014.0,
        "BUGEY 3": 2056939.0,
        "BUGEY 4": 1969524.0,
        "BUGEY 5": 1128451.0,
        "CATTENOM 1": 2256424.0,
        "CATTENOM 2": 2857092.0,
        "CATTENOM 3": 2905819.0,
        "CATTENOM 4": 777874.0,
        "CHINON 1": 1260103.0,
        "CHINON 2": 1999291.0,
        "CHINON 3": 1919653.0,
        "CHINON 4": 1900863.0,
        "CHOOZ 1": 2538635.0,
        "CHOOZ 2": 1430626.0,
        "CIVAUX 1": 3013022.0,
        "CIVAUX 2": 3107102.0,
        "CRUAS 1": 2025585.0,
        "CRUAS 2": 1374135.0,
        "CRUAS 3": 647656.0,
        "CRUAS 4": 2044663.0,
        "DAMPIERRE 1": 1604981.0,
        "DAMPIERRE 2": 950684.0,
        "DAMPIERRE 3": 2048595.0,
        "DAMPIERRE 4": 1884687.0,
        "FLAMANVILLE 1": 2000428.0,
        "FLAMANVILLE 2": 245.0,
        "GOLFECH 1": 2795963.0,
        "GOLFECH 2": 1845840.0,
        "GRAVELINES 1": 864035.0,
        "GRAVELINES 2": 1356235.0,
        "GRAVELINES 3": 2027171.0,
        "GRAVELINES 4": 1858387.0,
        "GRAVELINES 5": 2054525.0,
        "GRAVELINES 6": 1887817.0,
        "NOGENT 1": 2910657.0,
        "NOGENT 2": 2814381.0,
        "PALUEL 1": 47713.0,
        "PALUEL 2": 2760195.0,
        "PALUEL 3": 2845870.0,
        "PALUEL 4": 2738185.0,
        "PENLY 1": 2123048.0,
        "PENLY 2": 2885688.0,
        "ST ALBAN 1": 1594286.0,
        "ST ALBAN 2": 2799043.0,
        "ST LAURENT 1": 2000339.0,
        "ST LAURENT 2": 1801862.0,
        "TRICASTIN 1": 1208366.0,
        "TRICASTIN 2": 1976290.0,
        "TRICASTIN 3": 1814921.0,
        "TRICASTIN 4": 2093243.0,
        "FLAMANVILLE 3": 2178606.0
    },
    "cache_statut": {
        "BELLEVILLE 1": true,
        "BELLEVILLE 2": true,
        "BLAYAIS 1": true,
        "BLAYAIS 2": true,
        "BLAYAIS 3": false,
        "BLAYAIS 4": true,
        "BUGEY 2": true,
        "BUGEY 3": true,
        "BUGEY 4": true,
        "BUGEY 5": false,
        "CATTENOM 1": true,
        "CATTENOM 2": true,
        "CATTENOM 3": true,
        "CATTENOM 4": false,
        "CHINON 1": true,
        "CHINON 2": true,
        "CHINON 3": true,
        "CHINON 4": false,
        "CHOOZ 1": true,
        "CHOOZ 2": false,
        "CIVAUX 1": true,
        "CIVAUX 2": true,
        "CRUAS 1": true,
        "CRUAS 2": true,
        "CRUAS 3": false,
        "CRUAS 4": true,
        "DAMPIERRE 1": true,
        "DAMPIERRE 2": true,
        "DAMPIERRE 3": true,
        "DAMPIERRE 4": true,
        "FLAMANVILLE 1": true,
        "FLAMANVILLE 2": false,
        "GOLFECH 1": true,
        "GOLFECH 2": true,
        "GRAVELINES 1": true,
        "GRAVELINES 2": true,
        "GRAVELINES 3": true,
        "GRAVELINES 4": false,
        "GRAVELINES 5": true,
        "GRAVELINES 6": true,
        "NOGENT 1": true,
        "NOGENT 2": false,
        "PALUEL 1": false,
        "PALUEL 2": true,
        "PALUEL 3": true,
        "PALUEL 4": true,
        "PENLY 1": false,
        "PENLY 2": true,
        "ST ALBAN 1": false,
        "ST ALBAN 2": true,
        "ST LAURENT 1": true,
        "ST LAURENT 2": true,
        "TRICASTIN 1": false,
        "TRICASTIN 2": true,
        "TRICASTIN 3": true,
        "TRICASTIN 4": true,
        "FLAMANVILLE 3": true
    }
}