{
    "derniere_mise_a_jour": "26/05/2026 à 23:00",
    "horodatage_fin_recherche": "2026-05-26T23:00:00",
    "total_france_twh": 156.479,
    "nombre_centrales_actives": 18,
    "nombre_reacteurs_total": 57,
    "nombre_reacteurs_en_production": 44,
    "production_par_centrale_twh": {
        "GRAVELINES": 14.231,
        "PALUEL": 12.355,
        "CATTENOM": 12.147,
        "BUGEY": 10.18,
        "CRUAS": 9.771,
        "CHINON": 9.591,
        "DAMPIERRE": 9.497,
        "TRICASTIN": 9.177,
        "CIVAUX": 8.667,
        "BLAYAIS": 8.224,
        "BELLEVILLE": 7.933,
        "PENLY": 7.323,
        "FLAMANVILLE": 7.194,
        "NOGENT": 7.139,
        "GOLFECH": 6.875,
        "CHOOZ": 5.53,
        "ST ALBAN": 5.459,
        "ST LAURENT": 5.184
    },
    "cache_brut_mwh": {
        "BELLEVILLE 1": 4086226.0,
        "BELLEVILLE 2": 3847189.0,
        "BLAYAIS 1": 2366895.0,
        "BLAYAIS 2": 1966295.0,
        "BLAYAIS 3": 1077437.0,
        "BLAYAIS 4": 2812953.0,
        "BUGEY 2": 2579612.0,
        "BUGEY 3": 2896990.0,
        "BUGEY 4": 2680963.0,
        "BUGEY 5": 2022648.0,
        "CATTENOM 1": 3690864.0,
        "CATTENOM 2": 3500810.0,
        "CATTENOM 3": 4177255.0,
        "CATTENOM 4": 777877.0,
        "CHINON 1": 2084015.0,
        "CHINON 2": 2984450.0,
        "CHINON 3": 2617467.0,
        "CHINON 4": 1905392.0,
        "CHOOZ 1": 4099807.0,
        "CHOOZ 2": 1430626.0,
        "CIVAUX 1": 3930456.0,
        "CIVAUX 2": 4736895.0,
        "CRUAS 1": 2966890.0,
        "CRUAS 2": 2286471.0,
        "CRUAS 3": 1436715.0,
        "CRUAS 4": 3081342.0,
        "DAMPIERRE 1": 2525023.0,
        "DAMPIERRE 2": 1308412.0,
        "DAMPIERRE 3": 2801896.0,
        "DAMPIERRE 4": 2861264.0,
        "FLAMANVILLE 1": 3130670.0,
        "FLAMANVILLE 2": 195699.0,
        "GOLFECH 1": 3675648.0,
        "GOLFECH 2": 3199805.0,
        "GRAVELINES 1": 1915752.0,
        "GRAVELINES 2": 2191580.0,
        "GRAVELINES 3": 2964413.0,
        "GRAVELINES 4": 1858387.0,
        "GRAVELINES 5": 3116331.0,
        "GRAVELINES 6": 2184187.0,
        "NOGENT 1": 4324851.0,
        "NOGENT 2": 2814381.0,
        "PALUEL 1": 47826.0,
        "PALUEL 2": 3958988.0,
        "PALUEL 3": 4175358.0,
        "PALUEL 4": 4172583.0,
        "PENLY 1": 3088447.0,
        "PENLY 2": 4235016.0,
        "ST ALBAN 1": 1606859.0,
        "ST ALBAN 2": 3852021.0,
        "ST LAURENT 1": 2481827.0,
        "ST LAURENT 2": 2702463.0,
        "TRICASTIN 1": 1230728.0,
        "TRICASTIN 2": 3052844.0,
        "TRICASTIN 3": 2746151.0,
        "TRICASTIN 4": 2147658.0,
        "FLAMANVILLE 3": 3867793.0
    },
    "cache_statut": {
        "BELLEVILLE 1": true,
        "BELLEVILLE 2": true,
        "BLAYAIS 1": true,
        "BLAYAIS 2": false,
        "BLAYAIS 3": true,
        "BLAYAIS 4": true,
        "BUGEY 2": false,
        "BUGEY 3": true,
        "BUGEY 4": true,
        "BUGEY 5": true,
        "CATTENOM 1": true,
        "CATTENOM 2": false,
        "CATTENOM 3": true,
        "CATTENOM 4": false,
        "CHINON 1": true,
        "CHINON 2": true,
        "CHINON 3": true,
        "CHINON 4": true,
        "CHOOZ 1": true,
        "CHOOZ 2": false,
        "CIVAUX 1": true,
        "CIVAUX 2": true,
        "CRUAS 1": true,
        "CRUAS 2": true,
        "CRUAS 3": true,
        "CRUAS 4": true,
        "DAMPIERRE 1": true,
        "DAMPIERRE 2": true,
        "DAMPIERRE 3": true,
        "DAMPIERRE 4": true,
        "FLAMANVILLE 1": true,
        "FLAMANVILLE 2": true,
        "GOLFECH 1": false,
        "GOLFECH 2": true,
        "GRAVELINES 1": true,
        "GRAVELINES 2": false,
        "GRAVELINES 3": true,
        "GRAVELINES 4": false,
        "GRAVELINES 5": true,
        "GRAVELINES 6": true,
        "NOGENT 1": true,
        "NOGENT 2": false,
        "PALUEL 1": false,
        "PALUEL 2": true,
        "PALUEL 3": false,
        "PALUEL 4": true,
        "PENLY 1": true,
        "PENLY 2": true,
        "ST ALBAN 1": true,
        "ST ALBAN 2": true,
        "ST LAURENT 1": false,
        "ST LAURENT 2": true,
        "TRICASTIN 1": true,
        "TRICASTIN 2": true,
        "TRICASTIN 3": true,
        "TRICASTIN 4": false,
        "FLAMANVILLE 3": true
    }
}